toolkitbrazil.py
toolkitbrazil-0.0.3.dist-info/licenses/LICENSE.txt
toolkitbrazil-0.0.3.dist-info/METADATA
toolkitbrazil-0.0.3.dist-info/WHEEL
toolkitbrazil-0.0.3.dist-info/top_level.txt
toolkitbrazil-0.0.3.dist-info/RECORD
