Metadata-Version: 2.4
Name: toolkitbrazil
Version: 0.0.3
Summary: A Python module with a collection of useful tools for Brazilians (and anyone else who wants to use it)
Author-email: Ricardo Colombani <ricardo.colombani@gmail.com>
License-Expression: MIT
Project-URL: Homepage, https://github.com/coloric/toolkitbrazil
Project-URL: Repository, https://github.com/coloric/toolkitbrazil
Project-URL: Changelog, https://github.com/coloric/toolkitbrazil/blob/main/CHANGELOG.md
Project-URL: Issues, https://github.com/coloric/toolkitbrazil/issues
Keywords: library,utility,utilities
Requires-Python: >=3.10
License-File: LICENSE.txt
Dynamic: license-file
